{"id":41197,"name":"ozone","version":"1","target":"V4","no_of_instances":366,"no_of_features":13,"categorical_features":["V1","V2","V3"],"numeric_features":["V4","V5","V6","V7","V8","V9","V10","V11","V12","V13"],"variables_types":["factor","factor","factor","numeric","numeric","numeric","numeric","numeric","numeric","numeric","numeric","numeric","numeric"],"categorical_features_info":[{"factor_name":"V1","no_of_levels":12,"percentage_of_unique":3.3},{"factor_name":"V2","no_of_levels":31,"percentage_of_unique":8.5},{"factor_name":"V3","no_of_levels":7,"percentage_of_unique":1.9}],"categorical_missings":[],"numeric_missings":[{"column":"V4","no_of_missings":5,"percentage_of_missings":1.4},{"column":"V5","no_of_missings":12,"percentage_of_missings":3.3},{"column":"V7","no_of_missings":15,"percentage_of_missings":4.1},{"column":"V8","no_of_missings":2,"percentage_of_missings":0.5},{"column":"V9","no_of_missings":139,"percentage_of_missings":38},{"column":"V10","no_of_missings":15,"percentage_of_missings":4.1},{"column":"V11","no_of_missings":1,"percentage_of_missings":0.3},{"column":"V12","no_of_missings":14,"percentage_of_missings":3.8}],"no_of_missings":203,"no_of_instances_with_missings":163,"no_of_features_with_missings":8,"no_of_categorical_with_missings":0,"no_of_numeric_with_missings":8}
